{"base_01.md":"CQ9rFVdL","base_02.md":"Df7EBacI","base_03.md":"DlAZ4xCJ","base_04.md":"DN5VIaW-","base_05.md":"BlVUFmpn","base_06.md":"CGMhF8wH","base_07.md":"BTCSVu4E","base_08.md":"WSm31fE3","base_09.md":"CUJcDsP_","base_10.md":"CI5_4bMm","base_11.md":"DO3_8tp1","base_12.md":"Bhg5DJ0l","base_13.md":"DRSQIriH","base_14.md":"B80gj5x4","base_15.md":"BHTQsuDm","base_16.md":"BfECz0Su","base_17.md":"DEsyI2SY","base_18.md":"OOKGAKZS","base_index.md":"n8mG9yc7","framework_01.md":"BP18JoU2","framework_index.md":"DJvp81as","index.md":"CQoH-F7r","others_auto_release_notes.md":"BfWyQrbB","others_problems_archive.md":"DLlyoJtb","others_release_notes_template.md":"Bv8mbuYo","review_base_01.md":"DIf6_VOF","review_base_02.md":"BBI6cUHd","review_base_03.md":"D4jbF9gu","review_base_04.md":"DstJN5pB","review_base_05.md":"CeEHBFmq","review_base_06.md":"LOBTKBSs","review_base_07.md":"DJdOmhyp","review_base_08.md":"CHOikqOl","review_base_09.md":"Dftac9eJ","review_base_10.md":"CGMa2iY6","review_base_11.md":"BJ9mE1Z0","review_base_12.md":"B4YI4uqc","review_base_13.md":"3ILhUQhD","review_base_14.md":"CThjfULi","review_base_15.md":"CBbjVOSN","review_base_16.md":"BwYzIEjn","review_base_17.md":"HRY6tK4w","review_base_18.md":"CxhhibGp","review_framework_01.md":"DblNPhBP","review_framework_02.md":"B4LKH28u","review_index.md":"Dr8fglHV"}
